gnes/__init__.py
gnes/component.py
gnes/helper.py
gnes/uuid.py
gnes/base/__init__.py
gnes/cli/__init__.py
gnes/cli/api.py
gnes/cli/parser.py
gnes/client/__init__.py
gnes/client/base.py
gnes/client/cli.py
gnes/client/http.py
gnes/client/stream.py
gnes/composer/__init__.py
gnes/composer/base.py
gnes/composer/flask.py
gnes/composer/http.py
gnes/encoder/__init__.py
gnes/encoder/base.py
gnes/encoder/audio/__init__.py
gnes/encoder/audio/mfcc.py
gnes/encoder/audio/vggish.py
gnes/encoder/audio/vggish_cores/__init__.py
gnes/encoder/audio/vggish_cores/vggish_params.py
gnes/encoder/audio/vggish_cores/vggish_postprocess.py
gnes/encoder/audio/vggish_cores/vggish_slim.py
gnes/encoder/image/__init__.py
gnes/encoder/image/cvae.py
gnes/encoder/image/inception.py
gnes/encoder/image/onnx.py
gnes/encoder/image/torchvision.py
gnes/encoder/image/cvae_cores/__init__.py
gnes/encoder/image/cvae_cores/model.py
gnes/encoder/image/inception_cores/__init__.py
gnes/encoder/image/inception_cores/inception_utils.py
gnes/encoder/image/inception_cores/inception_v4.py
gnes/encoder/numeric/__init__.py
gnes/encoder/numeric/hash.py
gnes/encoder/numeric/pca.py
gnes/encoder/numeric/pooling.py
gnes/encoder/numeric/pq.py
gnes/encoder/numeric/quantizer.py
gnes/encoder/numeric/standarder.py
gnes/encoder/numeric/tf_pq.py
gnes/encoder/numeric/vlad.py
gnes/encoder/text/__init__.py
gnes/encoder/text/bert.py
gnes/encoder/text/char.py
gnes/encoder/text/flair.py
gnes/encoder/text/transformer.py
gnes/encoder/text/w2v.py
gnes/encoder/video/__init__.py
gnes/encoder/video/incep_mixture.py
gnes/encoder/video/inception.py
gnes/encoder/video/yt8m_feature_extractor.py
gnes/encoder/video/yt8m_model.py
gnes/encoder/video/mixture_core/__init__.py
gnes/encoder/video/mixture_core/model.py
gnes/encoder/video/yt8m_feature_extractor_cores/__init__.py
gnes/encoder/video/yt8m_feature_extractor_cores/inception_utils.py
gnes/encoder/video/yt8m_feature_extractor_cores/inception_v3.py
gnes/flow/__init__.py
gnes/flow/base.py
gnes-0.0.47.dist-info/LICENSE
gnes-0.0.47.dist-info/METADATA
gnes-0.0.47.dist-info/WHEEL
gnes-0.0.47.dist-info/entry_points.txt
gnes-0.0.47.dist-info/top_level.txt
gnes-0.0.47.dist-info/RECORD
