Metadata-Version: 2.1
Name: gnes
Version: 0.0.47
Summary: GNES is Generic Neural Elastic Search, a cloud-native semantic search system based on deep neural network.
Home-page: https://gnes.ai
Author: GNES team
Author-email: team@gnes.ai
License: Apache 2.0
Download-URL: https://github.com/gnes-ai/gnes/tags
Keywords: gnes cloud-native semantic search elastic neural-network encoding embedding serving
Platform: UNKNOWN
Classifier: Intended Audience :: Developers
Classifier: Intended Audience :: Education
Classifier: Intended Audience :: Science/Research
Classifier: Programming Language :: Python :: 3.5
Classifier: Programming Language :: Python :: 3.6
Classifier: Programming Language :: Python :: 3.7
Classifier: Programming Language :: Cython
Classifier: Programming Language :: Unix Shell
Classifier: Environment :: Console
Classifier: License :: OSI Approved :: Apache Software License
Classifier: Operating System :: OS Independent
Classifier: Topic :: Database :: Database Engines/Servers
Classifier: Topic :: Scientific/Engineering :: Artificial Intelligence
Classifier: Topic :: Internet :: WWW/HTTP :: Indexing/Search
Classifier: Topic :: Scientific/Engineering :: Image Recognition
Classifier: Topic :: Multimedia :: Video
Classifier: Topic :: Scientific/Engineering
Classifier: Topic :: Scientific/Engineering :: Mathematics
Classifier: Topic :: Software Development
Classifier: Topic :: Software Development :: Libraries
Classifier: Topic :: Software Development :: Libraries :: Python Modules
Requires-Dist: numpy
Requires-Dist: termcolor
Requires-Dist: protobuf
Requires-Dist: grpcio
Requires-Dist: ruamel.yaml (>=0.15.89)
Requires-Dist: pyzmq (>=17.1.0)
Provides-Extra: aiohttp
Requires-Dist: aiohttp ; extra == 'aiohttp'
Provides-Extra: all
Requires-Dist: annoy (==1.15.2) ; extra == 'all'
Requires-Dist: flair (>=0.4.1) ; extra == 'all'
Requires-Dist: peakutils ; extra == 'all'
Requires-Dist: memory-profiler (>=0.55.0) ; extra == 'all'
Requires-Dist: plyvel (>=1.0.5) ; extra == 'all'
Requires-Dist: onnxruntime ; extra == 'all'
Requires-Dist: jieba ; extra == 'all'
Requires-Dist: flask ; extra == 'all'
Requires-Dist: pytorch-transformers ; extra == 'all'
Requires-Dist: sklearn ; extra == 'all'
Requires-Dist: gputil (>=1.4.0) ; extra == 'all'
Requires-Dist: pylint ; extra == 'all'
Requires-Dist: imagehash (>=4.0) ; extra == 'all'
Requires-Dist: bert-serving-server (>=1.8.6) ; extra == 'all'
Requires-Dist: opencv-python (>=4.0.0) ; extra == 'all'
Requires-Dist: librosa (>=0.7.0) ; extra == 'all'
Requires-Dist: aiohttp ; extra == 'all'
Requires-Dist: scipy ; extra == 'all'
Requires-Dist: bert-serving-client (>=1.8.6) ; extra == 'all'
Requires-Dist: image ; extra == 'all'
Requires-Dist: psutil (>=5.6.1) ; extra == 'all'
Provides-Extra: annoy
Requires-Dist: annoy (==1.15.2) ; extra == 'annoy'
Provides-Extra: audio
Requires-Dist: librosa (>=0.7.0) ; extra == 'audio'
Provides-Extra: bert
Requires-Dist: bert-serving-server (>=1.8.6) ; extra == 'bert'
Requires-Dist: bert-serving-client (>=1.8.6) ; extra == 'bert'
Provides-Extra: chinese
Requires-Dist: jieba ; extra == 'chinese'
Provides-Extra: cn_nlp
Requires-Dist: jieba ; extra == 'cn_nlp'
Requires-Dist: bert-serving-server (>=1.8.6) ; extra == 'cn_nlp'
Requires-Dist: bert-serving-client (>=1.8.6) ; extra == 'cn_nlp'
Requires-Dist: pytorch-transformers ; extra == 'cn_nlp'
Requires-Dist: flair (>=0.4.1) ; extra == 'cn_nlp'
Provides-Extra: flair
Requires-Dist: flair (>=0.4.1) ; extra == 'flair'
Provides-Extra: flask
Requires-Dist: flask ; extra == 'flask'
Provides-Extra: http
Requires-Dist: flask ; extra == 'http'
Requires-Dist: aiohttp ; extra == 'http'
Provides-Extra: leveldb
Requires-Dist: plyvel (>=1.0.5) ; extra == 'leveldb'
Provides-Extra: nlp
Requires-Dist: bert-serving-server (>=1.8.6) ; extra == 'nlp'
Requires-Dist: bert-serving-client (>=1.8.6) ; extra == 'nlp'
Requires-Dist: flair (>=0.4.1) ; extra == 'nlp'
Requires-Dist: pytorch-transformers ; extra == 'nlp'
Provides-Extra: onnx
Requires-Dist: onnxruntime ; extra == 'onnx'
Provides-Extra: scipy
Requires-Dist: scipy ; extra == 'scipy'
Requires-Dist: sklearn ; extra == 'scipy'
Provides-Extra: test
Requires-Dist: pylint ; extra == 'test'
Requires-Dist: memory-profiler (>=0.55.0) ; extra == 'test'
Requires-Dist: psutil (>=5.6.1) ; extra == 'test'
Requires-Dist: gputil (>=1.4.0) ; extra == 'test'
Provides-Extra: transformers
Requires-Dist: pytorch-transformers ; extra == 'transformers'
Provides-Extra: vision
Requires-Dist: opencv-python (>=4.0.0) ; extra == 'vision'
Requires-Dist: imagehash (>=4.0) ; extra == 'vision'
Requires-Dist: image ; extra == 'vision'
Requires-Dist: peakutils ; extra == 'vision'
